<!--<?xml version="1.0" encoding="UTF-8"?>-->
<!--<beans xmlns="http://www.springframework.org/schema/beans" xmlns:xsi="http://www.w3.org/2001/XMLSchema-instance"-->
	   <!--xsi:schemaLocation="http://www.springframework.org/schema/beans-->
<!--http://www.springframework.org/schema/beans/spring-beans-3.0.xsd">-->
	<!--<bean id="memcachedClient" factory-bean="memcachedClientBuilder" factory-method="build" destroy-method="shutdown"/>-->
	<!--&lt;!&ndash;properties config   &ndash;&gt;-->
	<!--<bean class="org.springframework.beans.factory.config.PropertyPlaceholderConfigurer">-->
		<!--<property name="order" value="1"/>-->
		<!--<property name="ignoreUnresolvablePlaceholders" value="true"/>-->
		<!--<property name="locations">-->
			<!--<list>-->
				<!--<value>classpath:datasource.properties</value>-->
			<!--</list>-->
		<!--</property>-->
	<!--</bean>-->
	<!--&lt;!&ndash;Memcached配置 &ndash;&gt;-->
	<!--<bean id="memcachedClientBuilder" class="net.rubyeye.xmemcached.XMemcachedClientBuilder">-->
		<!--<constructor-arg>-->
			<!--<list>-->
				<!--<bean class="java.net.InetSocketAddress">-->
					<!--<constructor-arg>-->
						<!--<value>${memcached.server1.host}</value>-->
					<!--</constructor-arg>-->
					<!--<constructor-arg>-->
						<!--<value>${memcached.server1.port}</value>-->
					<!--</constructor-arg>-->
				<!--</bean>-->
			<!--</list>-->
		<!--</constructor-arg>-->
		<!--<constructor-arg>-->
			<!--<list>-->
				<!--<value>${memcached.server1.weight}</value>-->
			<!--</list>-->
		<!--</constructor-arg>-->
		<!--<property name="commandFactory">-->
			<!--<bean class="net.rubyeye.xmemcached.command.TextCommandFactory"/>-->
		<!--</property>-->
		<!--<property name="sessionLocator">-->
			<!--<bean class="net.rubyeye.xmemcached.impl.KetamaMemcachedSessionLocator"/>-->
		<!--</property>-->
		<!--<property name="connectionPoolSize" value="${memcached.connectionPoolSize}"/>-->
	<!--</bean>-->
<!--</beans>-->